IDENTITY
bacnet_proxy/__init__.py
bacnet_proxy/agent.py
volttron_bacnet_proxy-2.0.0rc0.dist-info/LICENSE
volttron_bacnet_proxy-2.0.0rc0.dist-info/METADATA
volttron_bacnet_proxy-2.0.0rc0.dist-info/WHEEL
volttron_bacnet_proxy-2.0.0rc0.dist-info/entry_points.txt
volttron_bacnet_proxy-2.0.0rc0.dist-info/RECORD
