Metadata-Version: 2.1
Name: volttron-bacnet-proxy
Version: 2.0.0rc0
Summary: BACnet Proxy is an agent that supports communication and management of BACnet devices.
Home-page: https://github.com/eclipse-volttron/volttron-bacnet-proxy
License: Apache-2.0
Keywords: volttron,agent
Author: VOLTTRON team
Author-email: volttron@pnnl.gov
Requires-Python: >=3.10,<4.0
Classifier: Intended Audience :: Developers
Classifier: Intended Audience :: Information Technology
Classifier: Intended Audience :: Other Audience
Classifier: Intended Audience :: Science/Research
Classifier: License :: OSI Approved :: Apache Software License
Classifier: Programming Language :: Python :: 3
Classifier: Programming Language :: Python :: 3.10
Classifier: Programming Language :: Python :: 3.11
Classifier: Programming Language :: Python :: 3.12
Classifier: Programming Language :: Python :: 3 :: Only
Requires-Dist: bacpypes (==0.16.7)
Requires-Dist: volttron-core (>=2.0.0rc0)
Project-URL: Repository, https://github.com/eclipse-volttron/volttron-bacnet-proxy
